backrun_sdk/__init__.py
backrun_sdk/api.py
backrun_sdk/client.py
backrun_sdk/constants.py
backrun_sdk/run.py
backrun_sdk/task.py
backrun_sdk/django/__init__.py
backrun_sdk/django/views.py
backrun_sdk/fastapi/__init__.py
backrun_sdk/flask/__init__.py
backrun_sdk-0.1.5.dist-info/METADATA
backrun_sdk-0.1.5.dist-info/WHEEL
backrun_sdk-0.1.5.dist-info/licenses/LICENSE
backrun_sdk-0.1.5.dist-info/RECORD
