Metadata-Version: 2.3
Name: backrun-sdk
Version: 0.1.5
Summary: The official Backrun Python SDK
Project-URL: Homepage, https://backrun.io
Author-email: Backrun <support@backrun.io>
License-Expression: Apache-2.0
License-File: LICENSE
Classifier: Intended Audience :: Developers
Classifier: License :: OSI Approved :: Apache Software License
Classifier: Operating System :: OS Independent
Classifier: Programming Language :: Python
Classifier: Programming Language :: Python :: 3.9
Classifier: Programming Language :: Python :: 3.10
Classifier: Programming Language :: Python :: 3.11
Classifier: Programming Language :: Python :: 3.12
Requires-Python: >=3.9
Requires-Dist: httpx[http2]<1.0,>=0.25
Requires-Dist: orjson<4,>=3.10
